escapa_alubia/__init__.py
escapa_alubia/__main__.py
escapa_alubia/game.py
escapa_alubia/assets/alubia.png
escapa_alubia/assets/alubia_mewing.png
escapa_alubia/assets/enemigo.png
escapa_alubia/assets/fondo.jpeg
escapa_alubia/assets/pistola.png
escapa_alubia-0.1.0.dist-info/METADATA
escapa_alubia-0.1.0.dist-info/WHEEL
escapa_alubia-0.1.0.dist-info/entry_points.txt
escapa_alubia-0.1.0.dist-info/top_level.txt
escapa_alubia-0.1.0.dist-info/RECORD
