Metadata-Version: 2.4
Name: escapa-alubia
Version: 0.1.0
Summary: Un juego en Pygame donde huyes de una alubia gigante.
Home-page: https://github.com/minionsito/Escapa-de-la-Alubia
Author: Minion
Author-email: Minion <ivangm2012@gmail.com>
License: MIT
Requires-Python: >=3.8
Requires-Dist: pygame-ce
